[{"neighborhood":"CORDOVIL","date":"07/12/2016"},{"neighborhood":"OLARIA","date":"06/30/2016"},{"neighborhood":"CAMPO GRANDE","date":"06/30/2016"},{"neighborhood":"GAMBOA+SANTO CRISTO","date":"06/27/2016"},{"neighborhood":"CAMPO GRANDE","date":"06/24/2016"},{"neighborhood":"SAO CONRADO","date":"06/24/2016"},{"neighborhood":"MONERO","date":"06/22/2016"},{"neighborhood":"ESTACIO","date":"06/22/2016"},{"neighborhood":"MONERO","date":"06/22/2016"},{"neighborhood":"MONERO","date":"06/22/2016"},{"neighborhood":"MONERO","date":"06/21/2016"},{"neighborhood":"CAMPO GRANDE","date":"06/17/2016"},{"neighborhood":"CAMPO GRANDE","date":"06/17/2016"},{"neighborhood":"CAMPO GRANDE","date":"06/17/2016"},{"neighborhood":"CAMPO GRANDE","date":"06/17/2016"},{"neighborhood":"CAMPO GRANDE","date":"06/17/2016"},{"neighborhood":"CAMPO GRANDE","date":"06/17/2016"},{"neighborhood":"CAMPO GRANDE","date":"06/17/2016"},{"neighborhood":"CAMPO GRANDE","date":"06/17/2016"},{"neighborhood":"CAMPO GRANDE","date":"06/17/2016"},{"neighborhood":"CATETE","date":"06/17/2016"},{"neighborhood":"CAMPO GRANDE","date":"06/17/2016"},{"neighborhood":"GAMBOA+SANTO CRISTO","date":"06/17/2016"},{"neighborhood":"CAMPO GRANDE","date":"06/14/2016"},{"neighborhood":"CAMPO GRANDE","date":"06/14/2016"},{"neighborhood":"CAMPO GRANDE","date":"06/13/2016"},{"neighborhood":"CAMPO GRANDE","date":"06/13/2016"},{"neighborhood":"CAMPO GRANDE","date":"06/13/2016"},{"neighborhood":"CAMPO GRANDE","date":"06/13/2016"},{"neighborhood":"CAMPO GRANDE","date":"06/13/2016"},{"neighborhood":"CAMPO GRANDE","date":"06/13/2016"},{"neighborhood":"CAMPO GRANDE","date":"06/13/2016"},{"neighborhood":"GAMBOA+SANTO CRISTO","date":"06/13/2016"},{"neighborhood":"CAMPO GRANDE","date":"06/13/2016"},{"neighborhood":"CAMPO GRANDE","date":"06/13/2016"},{"neighborhood":"MARE","date":"06/13/2016"},{"neighborhood":"CAMPO GRANDE","date":"06/13/2016"},{"neighborhood":"CAMPO GRANDE","date":"06/13/2016"},{"neighborhood":"CAMPO GRANDE","date":"06/13/2016"},{"neighborhood":"CAMPO GRANDE","date":"06/13/2016"},{"neighborhood":"MONERO","date":"06/13/2016"},{"neighborhood":"MONERO","date":"06/13/2016"},{"neighborhood":"PORTUGUESA","date":"06/13/2016"},{"neighborhood":"SULACAP","date":"06/01/2016"},{"neighborhood":"BOTAFOGO","date":"06/01/2016"},{"neighborhood":"ANCHIETA","date":"06/01/2016"},{"neighborhood":"GAMBOA+SANTO CRISTO","date":"05/23/2016"},{"neighborhood":"CENTRO","date":"05/23/2016"},{"neighborhood":"CAMPO GRANDE","date":"05/23/2016"},{"neighborhood":"GRAJAU","date":"05/16/2016"},{"neighborhood":"MONERO","date":"05/16/2016"},{"neighborhood":"ILHA DO GOVERNADOR","date":"05/16/2016"},{"neighborhood":"BOTAFOGO","date":"05/16/2016"},{"neighborhood":"RICARDO DE ALBUQUERQUE","date":"05/13/2016"},{"neighborhood":"GAMBOA+SANTO CRISTO","date":"05/13/2016"},{"neighborhood":"BOTAFOGO","date":"05/12/2016"},{"neighborhood":"GAMBOA+SANTO CRISTO","date":"05/12/2016"},{"neighborhood":"BOTAFOGO","date":"05/12/2016"},{"neighborhood":"ILHA DO GOVERNADOR","date":"05/12/2016"},{"neighborhood":"BOTAFOGO","date":"05/04/2016"},{"neighborhood":"TIJUCA","date":"05/04/2016"},{"neighborhood":"MARE","date":"05/04/2016"},{"neighborhood":"MARE","date":"05/04/2016"},{"neighborhood":"CAMPO GRANDE","date":"04/18/2016"},{"neighborhood":"JARDIM CARIOCA","date":"04/18/2016"},{"neighborhood":"JARDIM CARIOCA","date":"04/18/2016"},{"neighborhood":"JARDIM CARIOCA","date":"04/18/2016"},{"neighborhood":"ROCINHA","date":"04/14/2016"},{"neighborhood":"MARIA DA GRACA","date":"04/06/2016"},{"neighborhood":"REALENGO","date":"04/06/2016"},{"neighborhood":"REALENGO","date":"04/06/2016"},{"neighborhood":"ILHA DO GOVERNADOR","date":"03/30/2016"},{"neighborhood":"GAMBOA+SANTO CRISTO","date":"03/30/2016"},{"neighborhood":"ILHA DO GOVERNADOR","date":"03/30/2016"},{"neighborhood":"ILHA DO GOVERNADOR","date":"03/30/2016"},{"neighborhood":"ILHA DO GOVERNADOR","date":"03/30/2016"},{"neighborhood":"ILHA DO GOVERNADOR","date":"03/18/2016"},{"neighborhood":"ILHA DO GOVERNADOR","date":"03/18/2016"},{"neighborhood":"ILHA DO GOVERNADOR","date":"03/18/2016"},{"neighborhood":"PORTUGUESA","date":"03/16/2016"},{"neighborhood":"PRACA SECA","date":"03/16/2016"},{"neighborhood":"RICARDO DE ALBUQUERQUE","date":"03/09/2016"},{"neighborhood":"JARDIM GUANABARA","date":"03/09/2016"},{"neighborhood":"PAVUNA","date":"03/02/2016"},{"neighborhood":"FLAMENGO","date":"03/02/2016"},{"neighborhood":"CENTRO","date":"03/02/2016"},{"neighborhood":"CENTRO","date":"03/02/2016"},{"neighborhood":"JARDIM CARIOCA","date":"03/02/2016"},{"neighborhood":"FLAMENGO","date":"03/01/2016"},{"neighborhood":"FLAMENGO","date":"03/01/2016"},{"neighborhood":"ANCHIETA","date":"02/19/2016"},{"neighborhood":"CAMPO GRANDE","date":"02/19/2016"},{"neighborhood":"ANCHIETA","date":"02/19/2016"},{"neighborhood":"ANCHIETA","date":"02/19/2016"},{"neighborhood":"BOTAFOGO","date":"02/19/2016"},{"neighborhood":"TIJUCA","date":"12/21/2015"},{"neighborhood":"JARDIM GUANABARA","date":"12/18/2015"},{"neighborhood":"REALENGO","date":"12/18/2015"},{"neighborhood":"LARANJEIRAS","date":"12/10/2015"},{"neighborhood":"TODOS OS SANTOS","date":"12/10/2015"},{"neighborhood":"REALENGO","date":"12/10/2015"},{"neighborhood":"ITANHANGA","date":"12/08/2015"},{"neighborhood":"CAMPO GRANDE","date":"12/08/2015"},{"neighborhood":"PRACA SECA","date":"12/08/2015"},{"neighborhood":"CAJU","date":"12/08/2015"},{"neighborhood":"CAJU","date":"12/08/2015"},{"neighborhood":"CAMPO GRANDE","date":"11/23/2015"},{"neighborhood":"REALENGO","date":"11/16/2015"},{"neighborhood":"PILARES","date":"11/16/2015"},{"neighborhood":"TIJUCA","date":"11/16/2015"},{"neighborhood":"FREGUESIA","date":"11/06/2015"},{"neighborhood":"RIBEIRA","date":"11/06/2015"},{"neighborhood":"RIBEIRA","date":"11/05/2015"},{"neighborhood":"FLAMENGO","date":"11/05/2015"},{"neighborhood":"GAMBOA+SANTO CRISTO","date":"11/04/2015"},{"neighborhood":"ANCHIETA","date":"11/04/2015"},{"neighborhood":"CENTRO","date":"10/28/2015"},{"neighborhood":"CAMPO GRANDE","date":"10/28/2015"},{"neighborhood":"CENTRO","date":"10/28/2015"},{"neighborhood":"PRAIA DA BANDEIRA","date":"10/20/2015"},{"neighborhood":"PITANGUEIRAS","date":"10/20/2015"},{"neighborhood":"VILA VALQUEIRE","date":"10/20/2015"},{"neighborhood":"BENFICA","date":"10/14/2015"},{"neighborhood":"CURICICA","date":"10/08/2015"},{"neighborhood":"FLAMENGO","date":"10/07/2015"},{"neighborhood":"BOTAFOGO","date":"10/07/2015"},{"neighborhood":"IPANEMA","date":"10/02/2015"},{"neighborhood":"ANCHIETA","date":"10/01/2015"},{"neighborhood":"CAMPO GRANDE","date":"09/28/2015"},{"neighborhood":"CAMPO GRANDE","date":"09/28/2015"},{"neighborhood":"PECHINCHA","date":"09/28/2015"},{"neighborhood":"BANGU+GERICINO","date":"09/22/2015"},{"neighborhood":"BANGU+GERICINO","date":"09/22/2015"},{"neighborhood":"BANGU+GERICINO","date":"09/22/2015"},{"neighborhood":"REALENGO","date":"09/21/2015"},{"neighborhood":"PITANGUEIRAS","date":"09/17/2015"},{"neighborhood":"PITANGUEIRAS","date":"09/15/2015"},{"neighborhood":"REALENGO","date":"09/02/2015"},{"neighborhood":"FLAMENGO","date":"08/27/2015"},{"neighborhood":"TIJUCA","date":"08/25/2015"},{"neighborhood":"PECHINCHA","date":"08/25/2015"},{"neighborhood":"ESTACIO","date":"08/25/2015"},{"neighborhood":"CAMPO GRANDE","date":"08/25/2015"},{"neighborhood":"REALENGO","date":"08/25/2015"},{"neighborhood":"TIJUCA","date":"08/25/2015"},{"neighborhood":"TIJUCA","date":"08/25/2015"},{"neighborhood":"ILHA DO GOVERNADOR","date":"08/25/2015"},{"neighborhood":"RIBEIRA","date":"08/25/2015"},{"neighborhood":"CAMPO GRANDE","date":"07/08/2015"},{"neighborhood":"REALENGO","date":"06/22/2015"},{"neighborhood":"BOTAFOGO","date":"06/16/2015"},{"neighborhood":"GAMBOA+SANTO CRISTO","date":"06/10/2015"},{"neighborhood":"ILHA DO GOVERNADOR","date":"06/03/2015"},{"neighborhood":"VISTA ALEGRE","date":"06/03/2015"},{"neighborhood":"GAMBOA+SANTO CRISTO","date":"06/03/2015"},{"neighborhood":"BENFICA","date":"06/03/2015"},{"neighborhood":"BENFICA","date":"06/03/2015"},{"neighborhood":"GAMBOA+SANTO CRISTO","date":"06/03/2015"},{"neighborhood":"GAMBOA+SANTO CRISTO","date":"06/03/2015"},{"neighborhood":"GAMBOA+SANTO CRISTO","date":"06/03/2015"},{"neighborhood":"FLAMENGO","date":"06/02/2015"},{"neighborhood":"REALENGO","date":"06/02/2015"},{"neighborhood":"OSWALDO CRUZ","date":"06/02/2015"},{"neighborhood":"OSWALDO CRUZ","date":"06/02/2015"},{"neighborhood":"FLAMENGO","date":"06/02/2015"},{"neighborhood":"OSWALDO CRUZ","date":"05/22/2015"},{"neighborhood":"GAMBOA+SANTO CRISTO","date":"05/22/2015"},{"neighborhood":"GAMBOA+SANTO CRISTO","date":"05/22/2015"},{"neighborhood":"ACARI","date":"05/21/2015"},{"neighborhood":"JACAREPAGUA","date":"05/21/2015"},{"neighborhood":"BOTAFOGO","date":"05/07/2015"},{"neighborhood":"PENHA","date":"05/07/2015"},{"neighborhood":"ENGENHO DE DENTRO","date":"05/04/2015"},{"neighborhood":"TAQUARA","date":"04/27/2015"},{"neighborhood":"FREGUESIA","date":"04/22/2015"},{"neighborhood":"MONERO","date":"04/13/2015"},{"neighborhood":"GAMBOA+SANTO CRISTO","date":"04/13/2015"},{"neighborhood":"FREGUESIA","date":"04/13/2015"},{"neighborhood":"GALEAO","date":"04/13/2015"},{"neighborhood":"ANCHIETA","date":"04/13/2015"},{"neighborhood":"JACAREPAGUA","date":"04/13/2015"},{"neighborhood":"GAMBOA+SANTO CRISTO","date":"04/13/2015"},{"neighborhood":"MONERO","date":"04/13/2015"},{"neighborhood":"BANGU","date":"04/13/2015"},{"neighborhood":"CIDADE DE DEUS","date":"04/13/2015"},{"neighborhood":"GAMBOA+SANTO CRISTO","date":"04/13/2015"},{"neighborhood":"GAMBOA+SANTO CRISTO","date":"04/13/2015"},{"neighborhood":"MONERO","date":"04/13/2015"},{"neighborhood":"REALENGO","date":"04/13/2015"},{"neighborhood":"GAMBOA+SANTO CRISTO","date":"03/20/2015"},{"neighborhood":"BARRA DA TIJUCA","date":"03/19/2015"},{"neighborhood":"OSWALDO CRUZ","date":"03/12/2015"},{"neighborhood":"LARANJEIRAS","date":"03/06/2015"},{"neighborhood":"ILHA DO GOVERNADOR","date":"03/06/2015"},{"neighborhood":"LARANJEIRAS","date":"03/06/2015"},{"neighborhood":"BOTAFOGO","date":"03/06/2015"},{"neighborhood":"PRACA SECA","date":"03/05/2015"},{"neighborhood":"MARIA DA GRACA","date":"02/26/2015"},{"neighborhood":"GAMBOA+SANTO CRISTO","date":"02/26/2015"},{"neighborhood":"GAMBOA+SANTO CRISTO","date":"02/26/2015"},{"neighborhood":"CATUMBI","date":"02/26/2015"},{"neighborhood":"GAMBOA+SANTO CRISTO","date":"02/26/2015"},{"neighborhood":"GAMBOA+SANTO CRISTO","date":"02/26/2015"},{"neighborhood":"GAMBOA+SANTO CRISTO","date":"02/26/2015"},{"neighborhood":"SAO CRISTOVAO","date":"02/26/2015"},{"neighborhood":"GAMBOA+SANTO CRISTO","date":"02/25/2015"},{"neighborhood":"CENTRO","date":"12/11/2014"},{"neighborhood":"ESTACIO","date":"12/11/2014"},{"neighborhood":"GAMBOA+SANTO CRISTO","date":"12/11/2014"},{"neighborhood":"BOTAFOGO","date":"12/11/2014"},{"neighborhood":"JACAREPAGUA","date":"12/11/2014"},{"neighborhood":"BANGU","date":"12/11/2014"},{"neighborhood":"SANTA CRUZ","date":"12/10/2014"},{"neighborhood":"GAMBOA+SANTO CRISTO","date":"12/10/2014"},{"neighborhood":"REALENGO","date":"12/10/2014"},{"neighborhood":"GUARATIBA","date":"12/10/2014"},{"neighborhood":"RIBEIRA","date":"12/04/2014"},{"neighborhood":"GAMBOA+SANTO CRISTO","date":"12/04/2014"},{"neighborhood":"BANCARIOS","date":"12/04/2014"},{"neighborhood":"GLORIA","date":"10/29/2014"},{"neighborhood":"RECREIO DOS BANDEIRANTES","date":"10/29/2014"},{"neighborhood":"GAMBOA+SANTO CRISTO","date":"10/29/2014"},{"neighborhood":"JACAREPAGUA","date":"10/22/2014"},{"neighborhood":"SEPETIBA","date":"10/22/2014"},{"neighborhood":"GAMBOA+SANTO CRISTO","date":"10/22/2014"},{"neighborhood":"GAMBOA+SANTO CRISTO","date":"10/22/2014"},{"neighborhood":"MEIER","date":"10/22/2014"},{"neighborhood":"MEIER","date":"10/22/2014"},{"neighborhood":"BENTO RIBEIRO","date":"10/22/2014"},{"neighborhood":"GAMBOA+SANTO CRISTO","date":"10/15/2014"},{"neighborhood":"COSMOS","date":"10/15/2014"},{"neighborhood":"TIJUCA","date":"10/15/2014"},{"neighborhood":"GAMBOA+SANTO CRISTO","date":"10/15/2014"},{"neighborhood":"MADUREIRA","date":"10/15/2014"},{"neighborhood":"JOA","date":"07/16/2014"},{"neighborhood":"GAMBOA+SANTO CRISTO","date":"07/16/2014"},{"neighborhood":"GAMBOA+SANTO CRISTO","date":"07/16/2014"},{"neighborhood":"CENTRO","date":"06/04/2014"},{"neighborhood":"GAMBOA+SANTO CRISTO","date":"06/04/2014"},{"neighborhood":"GUARATIBA","date":"06/04/2014"},{"neighborhood":"PACIENCIA","date":"06/04/2014"},{"neighborhood":"PACIENCIA","date":"06/04/2014"},{"neighborhood":"GAMBOA+SANTO CRISTO","date":"06/04/2014"},{"neighborhood":"PRACA SECA","date":"06/04/2014"},{"neighborhood":"INHAUMA","date":"06/04/2014"},{"neighborhood":"LARANJEIRAS","date":"05/28/2014"},{"neighborhood":"LARANJEIRAS","date":"05/28/2014"},{"neighborhood":"ESTACIO","date":"05/23/2014"},{"neighborhood":"GAMBOA+SANTO CRISTO","date":"05/22/2014"},{"neighborhood":"JOA","date":"05/22/2014"},{"neighborhood":"GAMBOA+SANTO CRISTO","date":"05/22/2014"},{"neighborhood":"VIDIGAL","date":"05/22/2014"},{"neighborhood":"GAMBOA+SANTO CRISTO","date":"05/14/2014"},{"neighborhood":"COSMOS","date":"05/14/2014"},{"neighborhood":"COSMOS","date":"05/14/2014"},{"neighborhood":"ROCHA","date":"05/14/2014"},{"neighborhood":"GAMBOA+SANTO CRISTO","date":"05/14/2014"},{"neighborhood":"CACHAMBI","date":"05/14/2014"},{"neighborhood":"PENHA","date":"05/14/2014"},{"neighborhood":"COCOTA","date":"05/08/2014"},{"neighborhood":"GAMBOA+SANTO CRISTO","date":"05/08/2014"},{"neighborhood":"CAJU","date":"05/08/2014"},{"neighborhood":"GAMBOA+SANTO CRISTO","date":"05/08/2014"},{"neighborhood":"ESTACIO","date":"05/08/2014"},{"neighborhood":"GAMBOA+SANTO CRISTO","date":"04/30/2014"},{"neighborhood":"JARDIM GUANABARA","date":"04/25/2014"},{"neighborhood":"ESTACIO","date":"04/25/2014"},{"neighborhood":"GAMBOA+SANTO CRISTO","date":"04/25/2014"},{"neighborhood":"GAMBOA+SANTO CRISTO","date":"04/25/2014"},{"neighborhood":"INHAUMA","date":"04/25/2014"},{"neighborhood":"CAJU","date":"04/25/2014"},{"neighborhood":"GAMBOA+SANTO CRISTO","date":"04/25/2014"},{"neighborhood":"ESTACIO","date":"04/25/2014"},{"neighborhood":"CENTRO","date":"04/25/2014"},{"neighborhood":"CAMPO GRANDE","date":"04/25/2014"},{"neighborhood":"GALEAO","date":"04/25/2014"},{"neighborhood":"GAMBOA+SANTO CRISTO","date":"04/25/2014"},{"neighborhood":"BANCARIOS","date":"04/25/2014"},{"neighborhood":"BANCARIOS","date":"04/25/2014"},{"neighborhood":"TAQUARA","date":"04/03/2014"},{"neighborhood":"TAQUARA","date":"04/03/2014"},{"neighborhood":"MANGUINHOS","date":"04/03/2014"},{"neighborhood":"PRACA SECA","date":"04/02/2014"},{"neighborhood":"GAMBOA+SANTO CRISTO","date":"04/02/2014"},{"neighborhood":"CAMPO GRANDE","date":"03/26/2014"},{"neighborhood":"SANTA CRUZ","date":"03/26/2014"},{"neighborhood":"GAMBOA+SANTO CRISTO","date":"03/26/2014"},{"neighborhood":"GAMBOA+SANTO CRISTO","date":"03/19/2014"},{"neighborhood":"ILHA DO GOVERNADOR","date":"03/19/2014"},{"neighborhood":"CAMPO GRANDE","date":"03/19/2014"},{"neighborhood":"SANTA CRUZ","date":"03/19/2014"},{"neighborhood":"GAMBOA+SANTO CRISTO","date":"03/14/2014"},{"neighborhood":"GAMBOA+SANTO CRISTO","date":"03/14/2014"},{"neighborhood":"JARDIM CARIOCA","date":"03/14/2014"},{"neighborhood":"GAMBOA+SANTO CRISTO","date":"03/06/2014"},{"neighborhood":"GAMBOA+SANTO CRISTO","date":"03/06/2014"},{"neighborhood":"GAMBOA+SANTO CRISTO","date":"03/06/2014"},{"neighborhood":"GAMBOA+SANTO CRISTO","date":"03/06/2014"},{"neighborhood":"TODOS OS SANTOS","date":"03/06/2014"},{"neighborhood":"ROCHA","date":"03/06/2014"},{"neighborhood":"ILHA DO GOVERNADOR","date":"03/06/2014"},{"neighborhood":"ILHA DO GOVERNADOR","date":"03/06/2014"},{"neighborhood":"GAMBOA+SANTO CRISTO","date":"03/06/2014"},{"neighborhood":"CAMPO GRANDE","date":"03/06/2014"},{"neighborhood":"MARIA DA GRACA","date":"03/06/2014"},{"neighborhood":"LARANJEIRAS","date":"03/06/2014"},{"neighborhood":"LARANJEIRAS","date":"02/27/2014"},{"neighborhood":"GAMBOA+SANTO CRISTO","date":"02/27/2014"},{"neighborhood":"CENTRO","date":"12/13/2013"},{"neighborhood":"CAMPO GRANDE","date":"12/06/2013"},{"neighborhood":"GALEAO","date":"12/06/2013"},{"neighborhood":"COSMOS","date":"12/04/2013"},{"neighborhood":"GAMBOA+SANTO CRISTO","date":"12/04/2013"},{"neighborhood":"GAMBOA+SANTO CRISTO","date":"12/04/2013"},{"neighborhood":"ILHA DO GOVERNADOR","date":"11/22/2013"},{"neighborhood":"GAMBOA+SANTO CRISTO","date":"11/22/2013"},{"neighborhood":"GAMBOA+SANTO CRISTO","date":"11/22/2013"},{"neighborhood":"ILHA DO GOVERNADOR","date":"11/21/2013"},{"neighborhood":"GAMBOA+SANTO CRISTO","date":"11/21/2013"},{"neighborhood":"GAMBOA+SANTO CRISTO","date":"11/21/2013"},{"neighborhood":"ILHA DO GOVERNADOR","date":"11/21/2013"},{"neighborhood":"GAMBOA+SANTO CRISTO","date":"11/13/2013"},{"neighborhood":"GAMBOA+SANTO CRISTO","date":"11/13/2013"},{"neighborhood":"GAMBOA+SANTO CRISTO","date":"11/13/2013"},{"neighborhood":"CAMPO GRANDE","date":"11/13/2013"},{"neighborhood":"GAMBOA+SANTO CRISTO","date":"11/11/2013"},{"neighborhood":"GAMBOA+SANTO CRISTO","date":"11/11/2013"},{"neighborhood":"GAMBOA+SANTO CRISTO","date":"11/11/2013"},{"neighborhood":"QUINTINO","date":"11/08/2013"},{"neighborhood":"CACUIA","date":"11/08/2013"},{"neighborhood":"GAMBOA+SANTO CRISTO","date":"11/08/2013"},{"neighborhood":"GAMBOA+SANTO CRISTO","date":"11/08/2013"},{"neighborhood":"MARE","date":"11/06/2013"},{"neighborhood":"JARDIM CARIOCA","date":"11/06/2013"},{"neighborhood":"GAMBOA+SANTO CRISTO","date":"11/06/2013"},{"neighborhood":"JARDIM CARIOCA","date":"11/06/2013"},{"neighborhood":"GAMBOA+SANTO CRISTO","date":"10/18/2013"},{"neighborhood":"SAUDE","date":"10/18/2013"},{"neighborhood":"GAMBOA+SANTO CRISTO","date":"10/18/2013"},{"neighborhood":"BANGU","date":"10/18/2013"},{"neighborhood":"GAMBOA+SANTO CRISTO","date":"10/18/2013"},{"neighborhood":"JOA","date":"10/18/2013"},{"neighborhood":"HIGIENOPOLIS","date":"10/18/2013"},{"neighborhood":"JARDIM CARIOCA","date":"10/18/2013"},{"neighborhood":"GAMBOA+SANTO CRISTO","date":"10/18/2013"},{"neighborhood":"COELHO NETO","date":"10/18/2013"},{"neighborhood":"GAMBOA+SANTO CRISTO","date":"10/17/2013"},{"neighborhood":"GAMBOA+SANTO CRISTO","date":"10/17/2013"},{"neighborhood":"GAMBOA+SANTO CRISTO","date":"09/27/2013"},{"neighborhood":"JOA","date":"09/27/2013"},{"neighborhood":"CAMPO GRANDE","date":"09/25/2013"},{"neighborhood":"JOA","date":"09/25/2013"},{"neighborhood":"BARRA DE GUARATIBA","date":"09/25/2013"},{"neighborhood":"BOTAFOGO","date":"09/25/2013"},{"neighborhood":"ESTACIO","date":"09/19/2013"},{"neighborhood":"JOA","date":"09/19/2013"},{"neighborhood":"MANGUINHOS","date":"09/19/2013"},{"neighborhood":"GAMBOA+SANTO CRISTO","date":"09/18/2013"},{"neighborhood":"SANTA CRUZ","date":"09/18/2013"},{"neighborhood":"GAMBOA+SANTO CRISTO","date":"09/18/2013"},{"neighborhood":"CASCADURA","date":"09/05/2013"},{"neighborhood":"BANGU","date":"09/05/2013"},{"neighborhood":"JACAREPAGUA","date":"09/05/2013"},{"neighborhood":"QUINTINO","date":"09/04/2013"},{"neighborhood":"BANGU","date":"09/04/2013"},{"neighborhood":"OLARIA","date":"09/04/2013"},{"neighborhood":"BANGU","date":"09/04/2013"},{"neighborhood":"GALEAO","date":"09/03/2013"},{"neighborhood":"CASCADURA","date":"09/03/2013"},{"neighborhood":"HIGIENOPOLIS","date":"09/02/2013"},{"neighborhood":"SAUDE","date":"08/22/2013"},{"neighborhood":"COELHO NETO","date":"08/09/2013"},{"neighborhood":"BARRA DA TIJUCA","date":"08/09/2013"},{"neighborhood":"BANGU","date":"08/09/2013"},{"neighborhood":"ANCHIETA+COSTA BARROS","date":"08/09/2013"},{"neighborhood":"SAUDE","date":"08/09/2013"},{"neighborhood":"ILHA DO GOVERNADOR","date":"08/09/2013"},{"neighborhood":"CENTRO","date":"08/09/2013"},{"neighborhood":"ANCHIETA","date":"08/09/2013"},{"neighborhood":"VISTA ALEGRE","date":"08/09/2013"},{"neighborhood":"VISTA ALEGRE","date":"08/09/2013"},{"neighborhood":"BANGU","date":"08/09/2013"},{"neighborhood":"GAMBOA+SANTO CRISTO","date":"08/09/2013"},{"neighborhood":"SANTISSIMO","date":"07/10/2013"},{"neighborhood":"BANGU","date":"07/03/2013"},{"neighborhood":"SEPETIBA","date":"07/03/2013"},{"neighborhood":"TANQUE","date":"06/26/2013"},{"neighborhood":"BENTO RIBEIRO","date":"06/26/2013"},{"neighborhood":"BANGU","date":"06/26/2013"},{"neighborhood":"ILHA DO GOVERNADOR","date":"06/26/2013"},{"neighborhood":"RECREIO DOS BANDEIRANTES","date":"06/26/2013"},{"neighborhood":"TAQUARA","date":"06/26/2013"},{"neighborhood":"SANTA CRUZ","date":"06/26/2013"},{"neighborhood":"SENADOR CAMARA","date":"06/26/2013"},{"neighborhood":"GUARATIBA","date":"06/26/2013"},{"neighborhood":"MARE","date":"06/26/2013"},{"neighborhood":"CURICICA","date":"06/26/2013"},{"neighborhood":"CENTRO","date":"06/26/2013"},{"neighborhood":"GAMBOA+SANTO CRISTO","date":"06/26/2013"},{"neighborhood":"BARRA DA TIJUCA","date":"06/26/2013"},{"neighborhood":"COSTA BARROS","date":"06/26/2013"},{"neighborhood":"TODOS OS SANTOS","date":"06/26/2013"},{"neighborhood":"CAMPO GRANDE","date":"06/19/2013"},{"neighborhood":"COPACABANA","date":"06/12/2013"},{"neighborhood":"SAUDE","date":"06/12/2013"},{"neighborhood":"GAMBOA+SANTO CRISTO","date":"06/12/2013"},{"neighborhood":"RIACHUELO","date":"06/12/2013"},{"neighborhood":"CAMPO GRANDE","date":"06/12/2013"},{"neighborhood":"PILARES","date":"06/12/2013"},{"neighborhood":"COELHO NETO","date":"06/12/2013"},{"neighborhood":"GUARATIBA","date":"06/07/2013"},{"neighborhood":"MARACANA","date":"06/07/2013"},{"neighborhood":"SANTA CRUZ","date":"06/07/2013"},{"neighborhood":"SANTA CRUZ","date":"06/07/2013"},{"neighborhood":"VILA ISABEL","date":"06/06/2013"},{"neighborhood":"ANDARAI","date":"06/06/2013"},{"neighborhood":"TIJUCA","date":"06/06/2013"},{"neighborhood":"TANQUE","date":"06/06/2013"},{"neighborhood":"ANDARAI","date":"05/24/2013"},{"neighborhood":"OLARIA","date":"05/24/2013"},{"neighborhood":"PIEDADE","date":"05/24/2013"},{"neighborhood":"GAMBOA+SANTO CRISTO","date":"05/24/2013"},{"neighborhood":"GAMBOA+SANTO CRISTO","date":"05/24/2013"},{"neighborhood":"QUINTINO","date":"05/24/2013"},{"neighborhood":"PIEDADE","date":"05/24/2013"},{"neighborhood":"VILA ISABEL","date":"05/24/2013"},{"neighborhood":"CAJU","date":"05/24/2013"},{"neighborhood":"BANGU","date":"05/21/2013"},{"neighborhood":"BANGU","date":"05/21/2013"},{"neighborhood":"SAMPAIO","date":"05/21/2013"},{"neighborhood":"BANGU","date":"05/21/2013"},{"neighborhood":"SENADOR CAMARA","date":"05/21/2013"},{"neighborhood":"BANGU","date":"05/20/2013"},{"neighborhood":"VILA ISABEL","date":"05/20/2013"},{"neighborhood":"ESTACIO","date":"05/13/2013"},{"neighborhood":"LINS DE VASCONCELOS","date":"05/09/2013"},{"neighborhood":"PRACA SECA+TANQUE","date":"05/09/2013"},{"neighborhood":"MARACANA","date":"05/09/2013"},{"neighborhood":"GUARATIBA","date":"05/09/2013"},{"neighborhood":"VARGEM GRANDE","date":"05/09/2013"},{"neighborhood":"VILA ISABEL","date":"05/09/2013"},{"neighborhood":"MARE","date":"04/22/2013"},{"neighborhood":"CAJU","date":"04/22/2013"},{"neighborhood":"MARE","date":"04/22/2013"},{"neighborhood":"GAMBOA+SANTO CRISTO","date":"04/22/2013"},{"neighborhood":"MARE","date":"04/22/2013"},{"neighborhood":"GAMBOA+SANTO CRISTO","date":"04/22/2013"},{"neighborhood":"GAMBOA+SANTO CRISTO","date":"04/22/2013"},{"neighborhood":"GAMBOA+SANTO CRISTO","date":"04/22/2013"},{"neighborhood":"RECREIO DOS BANDEIRANTES","date":"04/19/2013"},{"neighborhood":"SANTA CRUZ","date":"04/16/2013"},{"neighborhood":"GAMBOA+SANTO CRISTO","date":"04/16/2013"},{"neighborhood":"GAMBOA+SANTO CRISTO","date":"04/16/2013"},{"neighborhood":"CAMPO GRANDE","date":"04/16/2013"},{"neighborhood":"CAMPO GRANDE","date":"04/16/2013"},{"neighborhood":"TANQUE","date":"04/11/2013"},{"neighborhood":"RECREIO DOS BANDEIRANTES","date":"04/11/2013"},{"neighborhood":"GAMBOA+SANTO CRISTO","date":"04/11/2013"},{"neighborhood":"GAMBOA+SANTO CRISTO","date":"04/04/2013"},{"neighborhood":"GAMBOA+SANTO CRISTO","date":"04/04/2013"},{"neighborhood":"GAMBOA+SANTO CRISTO","date":"04/04/2013"},{"neighborhood":"BANGU","date":"04/04/2013"},{"neighborhood":"GAMBOA+SANTO CRISTO","date":"04/04/2013"},{"neighborhood":"GAMBOA+SANTO CRISTO","date":"04/04/2013"},{"neighborhood":"GAMBOA+SANTO CRISTO","date":"04/04/2013"},{"neighborhood":"GAMBOA+SANTO CRISTO","date":"04/04/2013"},{"neighborhood":"GAMBOA+SANTO CRISTO","date":"04/04/2013"},{"neighborhood":"GAMBOA+SANTO CRISTO","date":"04/04/2013"},{"neighborhood":"GAMBOA+SANTO CRISTO","date":"04/04/2013"},{"neighborhood":"GAMBOA+SANTO CRISTO","date":"04/04/2013"},{"neighborhood":"ILHA DO GOVERNADOR","date":"03/13/2013"},{"neighborhood":"GAMBOA+SANTO CRISTO","date":"03/07/2013"},{"neighborhood":"GAMBOA+SANTO CRISTO","date":"03/07/2013"},{"neighborhood":"GAMBOA+SANTO CRISTO","date":"03/07/2013"},{"neighborhood":"GAMBOA+SANTO CRISTO","date":"03/01/2013"},{"neighborhood":"GAMBOA+SANTO CRISTO","date":"03/01/2013"},{"neighborhood":"GAMBOA+SANTO CRISTO","date":"03/01/2013"},{"neighborhood":"GAMBOA+SANTO CRISTO","date":"03/01/2013"},{"neighborhood":"GAMBOA+SANTO CRISTO","date":"02/25/2013"},{"neighborhood":"GAMBOA+SANTO CRISTO","date":"02/25/2013"},{"neighborhood":"GAMBOA+SANTO CRISTO","date":"02/25/2013"},{"neighborhood":"MEIER","date":"02/25/2013"},{"neighborhood":"ESTACIO","date":"02/25/2013"},{"neighborhood":"MEIER","date":"02/25/2013"}]
