[{"neighborhood":"ANCHIETA","date":"04/25/2016"},{"neighborhood":"RICARDO DE ALBUQUERQUE","date":"04/25/2016"},{"neighborhood":"ANCHIETA","date":"04/25/2016"},{"neighborhood":"ANCHIETA","date":"04/13/2016"},{"neighborhood":"ANCHIETA","date":"04/13/2016"},{"neighborhood":"ANCHIETA","date":"04/13/2016"},{"neighborhood":"RICARDO DE ALBUQUERQUE","date":"03/14/2016"},{"neighborhood":"RICARDO DE ALBUQUERQUE","date":"03/02/2016"},{"neighborhood":"ANCHIETA","date":"12/03/2015"},{"neighborhood":"ANCHIETA","date":"12/03/2015"},{"neighborhood":"ANCHIETA","date":"12/03/2015"},{"neighborhood":"ANCHIETA","date":"12/03/2015"},{"neighborhood":"ANCHIETA","date":"12/03/2015"},{"neighborhood":"ANCHIETA","date":"12/03/2015"},{"neighborhood":"RAMOS","date":"12/03/2015"},{"neighborhood":"ANCHIETA","date":"12/03/2015"},{"neighborhood":"ANCHIETA","date":"12/03/2015"},{"neighborhood":"ANCHIETA","date":"12/02/2015"},{"neighborhood":"ANCHIETA","date":"12/02/2015"},{"neighborhood":"BANGU","date":"11/16/2015"},{"neighborhood":"JOA","date":"11/16/2015"},{"neighborhood":"ANCHIETA","date":"11/16/2015"},{"neighborhood":"ANCHIETA","date":"11/16/2015"},{"neighborhood":"ANCHIETA","date":"11/16/2015"},{"neighborhood":"ANCHIETA","date":"11/16/2015"},{"neighborhood":"ANCHIETA","date":"11/16/2015"},{"neighborhood":"ANCHIETA","date":"11/16/2015"}]
