{
  "simple": [
    {
      "id": "1941/2016",
      "url": "/APL/Legislativos/scpro1316.nsf/249cb321f17965260325775900523a42/4c0a33ae8ed89a4e83257fe10069e479?OpenDocument",
      "description": "AUTORIZA O PODER EXECUTIVO A CRIAR O PROGRAMA DE INCLUSÃO ATRAVÉS DA LOCALIZAÇÃO E IDENTIFICAÇÃO DE PESSOAS COM DEFICIÊNCIA FÍSICA, BUSCANDO RESGUARDAR E GARANTIR O DIREITO À INCLUSÃO A TODOS OS DEFICIENTES  FÍSICOS, MESMO EM LUGARES MAIS CARENTES. =>20160301941 => {Comissão de Justiça e Redação Comissão de Administração e Assuntos Ligados ao Servidor Público Comissão dos Direitos da Pessoa com Deficiência Comissão de Ciência Tecnologia Comunicação e Informática Comissão de Transportes e Trânsito Comissão de Trabalho e Emprego Comissão de Esportes e Lazer Comissão de Educação e Cultura Comissão de Higiene Saúde Pública e Bem-Estar Social Comissão de Finanças Orçamento e Fiscalização Financeira  }",
      "date": "07/15/2016",
      "author": "VEREADOR RAPHAEL GATTÁS"
    },
    {
      "id": "1938/2016",
      "url": "/APL/Legislativos/scpro1316.nsf/249cb321f17965260325775900523a42/c028e537e9c3b0ea83257fdf00655bd6?OpenDocument",
      "description": "ALTERA DISPOSITIVOS DA LEI Nº 3.424, DE 18 DE JULHO DE 2002 =>20160301938 => {Comissão de Justiça e Redação Comissão de Administração e Assuntos Ligados ao Servidor Público Comissão de Abastecimento Indústria Comércio e Agricultura Comissão de Educação e Cultura Comissão de Esportes e Lazer Comissão de Finanças Orçamento e Fiscalização Financeira      }",
      "date": "07/14/2016",
      "author": "VEREADOR RAPHAEL GATTÁS"
    },
    {
      "id": "1937/2016",
      "url": "/APL/Legislativos/scpro1316.nsf/249cb321f17965260325775900523a42/2e008deb697d12ca83257fe000644e30?OpenDocument",
      "description": "INCLUI O ENSINO DE NOÇÕES ELEMENTARES SOBRE DIREITO CONSTITUCIONAL, DIREITO PENAL E CIDADANIA NO CURRÍCULO DO ENSINO FUNDAMENTAL DA REDE MUNICIPAL DE EDUCAÇÃO. =>20160301937 => {Comissão de Justiça e Redação Comissão de Administração e Assuntos Ligados ao Servidor Público Comissão de Educação e Cultura Comissão de Finanças Orçamento e Fiscalização Financeira        }",
      "date": "07/14/2016",
      "author": "VEREADOR RAPHAEL GATTÁS"
    },
    {
      "id": "1936/2016",
      "url": "/APL/Legislativos/scpro1316.nsf/249cb321f17965260325775900523a42/158921fc57c4232283257fdf0069f926?OpenDocument",
      "description": "DÁ O NOME DE PRAÇA REGINA CABRAL SANTOS (1915-2016), À PRAÇA INOMINADA, LOCALIZADA NO BAIRRO DE CAVALCANTI =>20160301936 => {Comissão de Justiça e Redação Comissão de Assuntos Urbanos Comissão de Educação e Cultura         }",
      "date": "07/14/2016",
      "author": "VEREADOR RAPHAEL GATTÁS"
    },
    {
      "id": "1916/2016",
      "url": "/APL/Legislativos/scpro1316.nsf/249cb321f17965260325775900523a42/4562dd8bfb2ac4cd83257fd1005f72a5?OpenDocument",
      "description": "INCLUI O DIA DO BAIRRO DE COPACABANA NO CALENDÁRIO OFICIAL DA CIDADE, CONSOLIDADO PELA LEI Nº 5.146/2010. =>20160301916 => {Comissão de Justiça e Redação Comissão de Administração e Assuntos Ligados ao Servidor Público Comissão de Educação e Cultura         }",
      "date": "06/28/2016",
      "author": "VEREADOR RAPHAEL GATTÁS"
    },
    {
      "id": "1915/2016",
      "url": "/APL/Legislativos/scpro1316.nsf/249cb321f17965260325775900523a42/f0b9112aa3a2822f83257fd1005e75a0?OpenDocument",
      "description": "DÁ O NOME DE PRAÇA LUIZ MENDES (RADIALISTA, JORNALISTA E COMENTARISTA ESPORTIVO) AO LOGRADOURO PÚBLICO INOMINADO FORMADO PELA CONFLUÊNCIA DAS RUAS RAUL POMPÉIA E SÁ FERREIRA NO BAIRRO DR COPABANA. =>20160301915 => {Comissão de Justiça e Redação Comissão de Assuntos Urbanos Comissão de Educação e Cultura         }",
      "date": "06/27/2016",
      "author": "VEREADOR RAPHAEL GATTÁS"
    },
    {
      "id": "1902/2016",
      "url": "/APL/Legislativos/scpro1316.nsf/249cb321f17965260325775900523a42/a5f83ea382beb9a883257fd30072d815?OpenDocument",
      "description": "DÁ O NOME DE PRAÇA CARLITO ROCHA – CARLOS MARTINS DA ROCHA, À PRAÇA INOMINADA, LOCALIZADA NA AVENIDA VENCESLAU BRÁS, NO BAIRRO DE BOTAFOGO. =>20160301902 => {Comissão de Justiça e Redação Comissão de Assuntos Urbanos Comissão de Educação e Cultura         }",
      "date": "06/24/2016",
      "author": "VEREADOR RAPHAEL GATTÁS"
    }
  ]
}
